src/__init__.py
src/histoBoxPlot.py
histoboxplot-1.2.dist-info/LICENSE.txt
histoboxplot-1.2.dist-info/METADATA
histoboxplot-1.2.dist-info/WHEEL
histoboxplot-1.2.dist-info/top_level.txt
histoboxplot-1.2.dist-info/RECORD
