Metadata-Version: 2.1
Name: histoboxplot
Version: 1.2
Summary: A Python package to create combined histogram and boxplot visualization
Home-page: https://github.com/atugharajohn/HistoBoxPlot
Author: John Atughara
Author-email: atugharajohn@gmail.com
License: Apache License, Version 2.0
Keywords: histogram boxplot visualization matplotlib seaborn
Classifier: Programming Language :: Python :: 3
Classifier: License :: OSI Approved :: Apache Software License
Classifier: Operating System :: OS Independent
Requires-Python: >=3.6
License-File: LICENSE.txt
Requires-Dist: matplotlib >=3.1.1
Requires-Dist: seaborn >=0.9.0
